odoo/addons/web_copy_confirm/README.rst
odoo/addons/web_copy_confirm/__init__.py
odoo/addons/web_copy_confirm/__manifest__.py
odoo/addons/web_copy_confirm/i18n/de.po
odoo/addons/web_copy_confirm/i18n/fr.po
odoo/addons/web_copy_confirm/i18n/fr_FR.po
odoo/addons/web_copy_confirm/i18n/web_copy_confirm.pot
odoo/addons/web_copy_confirm/readme/CONTRIBUTORS.rst
odoo/addons/web_copy_confirm/readme/DESCRIPTION.rst
odoo/addons/web_copy_confirm/readme/HISTORY.rst
odoo/addons/web_copy_confirm/readme/newsfragments/.gitkeep
odoo/addons/web_copy_confirm/static/description/icon.png
odoo/addons/web_copy_confirm/static/description/index.html
odoo/addons/web_copy_confirm/static/src/js/web_copy_confirm.js
odoo/addons/web_copy_confirm/static/tests/confirm_tests.js
odoo/addons/web_copy_confirm/views/assets.xml
odoo14_addon_web_copy_confirm-14.0.1.0.1.dev8.dist-info/METADATA
odoo14_addon_web_copy_confirm-14.0.1.0.1.dev8.dist-info/WHEEL
odoo14_addon_web_copy_confirm-14.0.1.0.1.dev8.dist-info/top_level.txt
odoo14_addon_web_copy_confirm-14.0.1.0.1.dev8.dist-info/RECORD
